azureml/__init__.py
azureml/_third_party_notice/ThirdPartyNotice-Widgets.html
azureml/train/__init__.py
azureml/train/widgets/__init__.py
azureml/train/widgets/_constants.py
azureml/train/widgets/_platform.py
azureml/train/widgets/_transformer.py
azureml/train/widgets/_universal_widgets.py
azureml/train/widgets/_widgets.py
azureml/train/widgets/run_details.py
azureml/train/widgets/static/extension.js
azureml/train/widgets/static/index.js
azureml/train/widgets/static/packages/labextension/azureml_train_widgets-1.0.0.tgz
azureml_train_widgets-0.1.74.data/data/share/jupyter/lab/extensions/azureml_train_widgets-1.0.0.tgz
azureml_train_widgets-0.1.74.data/data/share/jupyter/nbextensions/azureml_train_widgets/extension.js
azureml_train_widgets-0.1.74.data/data/share/jupyter/nbextensions/azureml_train_widgets/index.js
azureml_train_widgets-0.1.74.dist-info/DESCRIPTION.rst
azureml_train_widgets-0.1.74.dist-info/LICENSE.txt
azureml_train_widgets-0.1.74.dist-info/METADATA
azureml_train_widgets-0.1.74.dist-info/RECORD
azureml_train_widgets-0.1.74.dist-info/WHEEL
azureml_train_widgets-0.1.74.dist-info/metadata.json
azureml_train_widgets-0.1.74.dist-info/top_level.txt
