Metadata-Version: 2.0
Name: azureml-train-widgets
Version: 0.1.74
Summary: azureml train widgets
Home-page: https://docs.microsoft.com/en-us/azure/machine-learning/service/
Author: Microsoft Corp
License: Proprietary https://aka.ms/azureml-sdk-license
Keywords: ipython,jupyter,widgets
Platform: UNKNOWN
Classifier: Development Status :: 4 - Beta
Classifier: Framework :: IPython
Classifier: Intended Audience :: Developers
Classifier: Intended Audience :: Science/Research
Classifier: Topic :: Multimedia :: Graphics
Classifier: Programming Language :: Python :: 3
Classifier: Programming Language :: Python :: 3.3
Classifier: Programming Language :: Python :: 3.4
Classifier: Programming Language :: Python :: 3.5
Requires-Dist: ipywidgets (>=7.0.0)
Requires-Dist: azureml-train-core (==0.1.74.*)
Requires-Dist: azureml-core (==0.1.74.*)
Requires-Dist: azureml-pipeline (==0.1.74.*)
Requires-Dist: azureml-telemetry (==0.1.74.*)
